missing_mnv/__init__.py
missing_mnv/__main__.py
missing_mnv-0.0.1.dist-info/LICENSE.txt
missing_mnv-0.0.1.dist-info/METADATA
missing_mnv-0.0.1.dist-info/WHEEL
missing_mnv-0.0.1.dist-info/top_level.txt
missing_mnv-0.0.1.dist-info/RECORD
