Metadata-Version: 2.1
Name: missing-mnv
Version: 0.0.1
Summary: Missing Values Handler
Home-page: UNKNOWN
Author: Manav Upadhyay
Author-email: manavupadhyay5@gmail.com
License: UNKNOWN
Platform: UNKNOWN
Classifier: Programming Language :: Python :: 3
Classifier: License :: OSI Approved :: MIT License
Classifier: Operating System :: OS Independent
Requires-Python: >=3.6
